<bean class="org.apache.ignite.configuration.IgniteConfiguration">

    <property name="workDirectory" value="/ignite/work"/>

    <property name="dataStorageConfiguration">
        <bean class="org.apache.ignite.configuration.DataStorageConfiguration">
            <property name="defaultDataRegionConfiguration">
                <bean class="org.apache.ignite.configuration.DataRegionConfiguration">
                    <property name="persistenceEnabled" value="true"/>
                </bean>
            </property>

            <property name="walPath" value="/ignite/wal"/>
            <property name="walArchivePath" value="/ignite/walarchive"/>
        </bean>

    </property>

    <property name="discoverySpi">
        <bean class="org.apache.ignite.spi.discovery.tcp.TcpDiscoverySpi">
            <property name="ipFinder">
                <bean class="org.apache.ignite.spi.discovery.tcp.ipfinder.kubernetes.TcpDiscoveryKubernetesIpFinder">
                    <property name="namespace" value="ignite"/>
                    <property name="serviceName" value="ignite-service"/>
                </bean>
            </property>
        </bean>
    </property>

</bean>